donut_ai_evaluate/__init__.py
donut_ai_evaluate/_agent/__init__.py
donut_ai_evaluate/_agent/digitize_evaluation_agents.py
donut_ai_evaluate/_agent/field_comparison_agent.py
donut_ai_evaluate/_agent/_prompts/__init__.py
donut_ai_evaluate/_agent/_prompts/digitize_prompts.py
donut_ai_evaluate/_agent/_schemas/__init__.py
donut_ai_evaluate/_agent/_schemas/digitize_schemas.py
donut_ai_evaluate/_common/__init__.py
donut_ai_evaluate/_common/decorators.py
donut_ai_evaluate/_common/enums.py
donut_ai_evaluate/_common/eval_logger.py
donut_ai_evaluate/data_entry/__init__.py
donut_ai_evaluate/data_entry/core.py
donut_ai_evaluate/redact/__init__.py
donut_ai_evaluate/redact/core.py
donut_ai_evaluate/redact/models.py
donut_ai_evaluate/redact/utils.py
donut_ai_evaluate-0.1.5.dist-info/METADATA
donut_ai_evaluate-0.1.5.dist-info/WHEEL
donut_ai_evaluate-0.1.5.dist-info/top_level.txt
donut_ai_evaluate-0.1.5.dist-info/RECORD
