Metadata-Version: 2.4
Name: donut-ai-evaluate
Version: 0.1.5
Summary: Donut packages for evaluating the output of data entry and redact.
Author-email: Zain Ullah <zain.ullah@siparadigm.com>, Maaz Ullah <maaz.ullah@siparadigm.com>, Ameer Hamza <ameer.hamza@siparadigm.com>
License: MIT
Requires-Python: >=3.10
Requires-Dist: annotated-types==0.7.0
Requires-Dist: google-ai-generativelanguage==0.6.18
Requires-Dist: google-cloud-vision==3.3.0
Requires-Dist: httpx==0.28.1
Requires-Dist: json_repair==0.41.0
Requires-Dist: jsonpatch==1.33
Requires-Dist: langchain==0.3.23
Requires-Dist: langchain-google-genai==2.1.2
Requires-Dist: numpy==2.2.6
Requires-Dist: opencv-python-headless>=4.11
Requires-Dist: orjson==3.10.18
Requires-Dist: pandas==2.2.3
Requires-Dist: pdf2image==1.17.0
Requires-Dist: pillow==11.2.1
Requires-Dist: pydantic==2.8.0
Requires-Dist: python-dotenv==1.1.0
Requires-Dist: PyYAML==6.0.2
Requires-Dist: RapidFuzz==3.13.0
Requires-Dist: requests==2.32.3
Requires-Dist: tenacity==9.1.2
